LICENSE
MANIFEST.in
README.rst
setup.py
tests.py
boxview/__init__.py
boxview/boxview.py
boxview/utils.py
python_boxview.egg-info/PKG-INFO
python_boxview.egg-info/SOURCES.txt
python_boxview.egg-info/dependency_links.txt
python_boxview.egg-info/not-zip-safe
python_boxview.egg-info/requires.txt
python_boxview.egg-info/top_level.txt